README.md
sciplot.py
parameters/__init__.py
sciplot/__init__.py
sciplot/main.py
sciplot/sciplot.py
sciplot/parameters/__init__.py
sciplot/parameters/basic.yml
sciplot/parameters/colors.yml
sciplot/parameters/colors_dark.yml
sciplot/parameters/colors_light.yml
sciplot/parameters/fonts_sans_serif.yml
sciplot/parameters/fonts_serif.yml
sciplot/parameters/latex_sans_serif.yml
sciplot/parameters/latex_serif.yml
sciplot/parameters/typesetting.yml
neat_sciplots-0.7.8.dist-info/LICENSE.txt
neat_sciplots-0.7.8.dist-info/METADATA
neat_sciplots-0.7.8.dist-info/WHEEL
neat_sciplots-0.7.8.dist-info/top_level.txt
neat_sciplots-0.7.8.dist-info/RECORD
