Metadata-Version: 2.1
Name: neat-sciplots
Version: 0.7.8
Summary: Neatly format Matplotlib scientific plots
Home-page: https://github.com/andreasfuhr/neat-sciplots
Author: Andreas Führ
Author-email: andreas.fuhr@outlook.com
License: MIT
Platform: UNKNOWN
Classifier: Programming Language :: Python :: 3.7
Classifier: License :: OSI Approved :: MIT License
Classifier: Operating System :: OS Independent
Classifier: Development Status :: 4 - Beta
Classifier: Natural Language :: English
Classifier: Framework :: Matplotlib
Classifier: Topic :: Scientific/Engineering
Requires-Python: >=3.7
Requires-Dist: matplotlib (>=3.3.4)
Requires-Dist: pyyaml
Requires-Dist: seaborn
